aceye/ARP Adjacency Endpoints/CSV/.gitignore
aceye/ARP Adjacency Endpoints/HTML/.gitignore
aceye/ARP Adjacency Endpoints/JSON/.gitignore
aceye/ARP Adjacency Endpoints/Markdown/.gitignore
aceye/ARP Adjacency Endpoints/Mindmap/.gitignore
aceye/ARP Adjacency Endpoints/YAML/.gitignore
aceye/ARP Database/CSV/.gitignore
aceye/ARP Database/HTML/.gitignore
aceye/ARP Database/JSON/.gitignore
aceye/ARP Database/Markdown/.gitignore
aceye/ARP Database/Mindmap/.gitignore
aceye/ARP Database/YAML/.gitignore
aceye/ARP Domain/CSV/.gitignore
aceye/ARP Domain/HTML/.gitignore
aceye/ARP Domain/JSON/.gitignore
aceye/ARP Domain/Markdown/.gitignore
aceye/ARP Domain/Mindmap/.gitignore
aceye/ARP Domain/YAML/.gitignore
aceye/ARP Entity/CSV/.gitignore
aceye/ARP Entity/HTML/.gitignore
aceye/ARP Entity/JSON/.gitignore
aceye/ARP Entity/Markdown/.gitignore
aceye/ARP Entity/Mindmap/.gitignore
aceye/ARP Entity/YAML/.gitignore
aceye/ARP Instances/CSV/.gitignore
aceye/ARP Instances/HTML/.gitignore
aceye/ARP Instances/JSON/.gitignore
aceye/ARP Instances/Markdown/.gitignore
aceye/ARP Instances/Mindmap/.gitignore
aceye/ARP Instances/YAML/.gitignore
aceye/ARP Interfaces/CSV/.gitignore
aceye/ARP Interfaces/HTML/.gitignore
aceye/ARP Interfaces/JSON/.gitignore
aceye/ARP Interfaces/Markdown/.gitignore
aceye/ARP Interfaces/Mindmap/.gitignore
aceye/ARP Interfaces/YAML/.gitignore
aceye/Access Bundle Groups/CSV/.gitignore
aceye/Access Bundle Groups/HTML/.gitignore
aceye/Access Bundle Groups/JSON/.gitignore
aceye/Access Bundle Groups/Markdown/.gitignore
aceye/Access Bundle Groups/Mindmap/.gitignore
aceye/Access Bundle Groups/YAML/.gitignore
aceye/Access Control Entities/CSV/.gitignore
aceye/Access Control Entities/HTML/.gitignore
aceye/Access Control Entities/JSON/.gitignore
aceye/Access Control Entities/Markdown/.gitignore
aceye/Access Control Entities/Mindmap/.gitignore
aceye/Access Control Entities/YAML/.gitignore
aceye/Access Control Instances/CSV/.gitignore
aceye/Access Control Instances/HTML/.gitignore
aceye-2.0.2.dist-info/entry_points.txt
aceye-2.0.2.dist-info/LICENSE
aceye-2.0.2.dist-info/WHEEL
aceye-2.0.2.dist-info/METADATA
aceye-2.0.2.dist-info/RECORD
